x2paddle/__init__.py
x2paddle/convert.py
x2paddle/models.py
x2paddle/torch2paddle.py
x2paddle/utils.py
x2paddle/core/__init__.py
x2paddle/core/graph.py
x2paddle/core/program.py
x2paddle/core/util.py
x2paddle/decoder/__init__.py
x2paddle/decoder/caffe_decoder.py
x2paddle/decoder/caffe_pb2.py
x2paddle/decoder/caffe_shape_inference.py
x2paddle/decoder/onnx_decoder.py
x2paddle/decoder/onnx_shape_inference.py
x2paddle/decoder/pytorch_decoder.py
x2paddle/decoder/tf_decoder.py
x2paddle/op_mapper/__init__.py
x2paddle/op_mapper/caffe2paddle/__init__.py
x2paddle/op_mapper/caffe2paddle/caffe_op_mapper.py
x2paddle/op_mapper/caffe2paddle/caffe_custom_layer/__init__.py
x2paddle/op_mapper/caffe2paddle/caffe_custom_layer/detectionoutput.py
x2paddle/op_mapper/caffe2paddle/caffe_custom_layer/normalize.py
x2paddle/op_mapper/caffe2paddle/caffe_custom_layer/priorbox.py
x2paddle/op_mapper/caffe2paddle/caffe_custom_layer/roipooling.py
x2paddle/op_mapper/caffe2paddle/caffe_custom_layer/select.py
x2paddle/op_mapper/onnx2paddle/__init__.py
x2paddle/op_mapper/onnx2paddle/onnx_op_mapper.py
x2paddle/op_mapper/onnx2paddle/opset10.py
x2paddle/op_mapper/onnx2paddle/opset11.py
x2paddle/op_mapper/onnx2paddle/opset12.py
x2paddle/op_mapper/onnx2paddle/opset13.py
x2paddle/op_mapper/onnx2paddle/opset14.py
x2paddle/op_mapper/onnx2paddle/opset15.py
x2paddle/op_mapper/onnx2paddle/opset7.py
x2paddle/op_mapper/onnx2paddle/opset8.py
x2paddle/op_mapper/onnx2paddle/opset9.py
x2paddle/op_mapper/onnx2paddle/opset_legacy.py
x2paddle/op_mapper/onnx2paddle/onnx_custom_layer/__init__.py
x2paddle/op_mapper/onnx2paddle/onnx_custom_layer/nms.py
x2paddle/op_mapper/onnx2paddle/onnx_custom_layer/one_hot.py
x2paddle/op_mapper/onnx2paddle/onnx_custom_layer/pad_all_dim2.py
x2paddle/op_mapper/onnx2paddle/onnx_custom_layer/pad_all_dim4.py
x2paddle/op_mapper/onnx2paddle/onnx_custom_layer/pad_all_dim4_one_input.py
x2paddle/op_mapper/onnx2paddle/onnx_custom_layer/pad_two_input.py
x2paddle-1.6.0.dist-info/AUTHORS.md
x2paddle-1.6.0.dist-info/LICENSE
x2paddle-1.6.0.dist-info/METADATA
x2paddle-1.6.0.dist-info/WHEEL
x2paddle-1.6.0.dist-info/entry_points.txt
x2paddle-1.6.0.dist-info/top_level.txt
x2paddle-1.6.0.dist-info/RECORD
