Metadata-Version: 2.1
Name: x2paddle
Version: 1.6.0
Summary: a toolkit for converting trained model to PaddlePaddle from other deep learning frameworks.
Home-page: https://github.com/PaddlePaddle/x2paddle
Author: PaddlePaddle Developer Community
Author-email: ext_paddle_oss@baidu.com
License: Apache 2.0
Classifier: Programming Language :: Python :: 3
Classifier: License :: OSI Approved :: Apache Software License
Classifier: Operating System :: OS Independent
License-File: LICENSE
License-File: AUTHORS.md
Requires-Dist: sympy
Requires-Dist: packaging
